quick_ml/__init__.py
quick_ml/Classification/__init__.py
quick_ml/Classification/augments.py
quick_ml/Classification/begin_device.py
quick_ml/Classification/begin_tpu.py
quick_ml/Classification/callbacks.py
quick_ml/Classification/k_fold_training.py
quick_ml/Classification/load_keras_effnets.py
quick_ml/Classification/load_models_quick.py
quick_ml/Classification/predictions.py
quick_ml/Classification/tfrecords_maker.py
quick_ml/Classification/training_predictions.py
quick_ml/Classification/utils.py
quick_ml/Classification/visualize_and_check_data.py
quick_ml/Classification/data/__init__.py
quick_ml/Classification/data/numpy/__init__.py
quick_ml/Classification/data/tf_data/__init__.py
quick_ml/Classification/data/tfrecords/__init__.py
quick_ml/Classification/data/tfrecords/tfloader.py
quick_ml/Classification/data/tfrecords/tfrecords_maker.py
quick_ml/Classification/data/tfrecords/visualize_and_check_data.py
quick_ml/Classification/models/__init__.py
quick_ml/Classification/models/load_models_quick.py
quick_ml/Classification/models/newPython3.py
quick_ml/Classification/models/predictions.py
quick_ml/Classification/models/training_predictions.py
quick_ml/Classification/models/pretrained/__init__.py
quick_ml/Classification/models/pretrained/download_model_weights.py
quick_ml/Classification/models/pretrained/alexnet/__init__.py
quick_ml/Classification/models/pretrained/alexnet/alexnet.py
quick_ml/Classification/models/pretrained/densenet/__init__.py
quick_ml/Classification/models/pretrained/densenet/densenet121.py
quick_ml/Classification/models/pretrained/densenet/densenet169.py
quick_ml/Classification/models/pretrained/densenet/densenet201.py
quick_ml/Classification/models/pretrained/googlenet/__init__.py
quick_ml/Classification/models/pretrained/inception/__init__.py
quick_ml/Classification/models/pretrained/inception/inceptionresnetv2.py
quick_ml/Classification/models/pretrained/inception/inceptionv3.py
quick_ml/Classification/models/pretrained/mobilenet/__init__.py
quick_ml-1.3.33.dist-info/licenses/LICENSE
quick_ml-1.3.33.dist-info/METADATA
quick_ml-1.3.33.dist-info/WHEEL
quick_ml-1.3.33.dist-info/top_level.txt
quick_ml-1.3.33.dist-info/RECORD
