Metadata-Version: 2.4
Name: quick_ml
Version: 1.3.33
Summary: quick_ml : Computer Vision For Everyone. Official Website -> www.antoreepjana.wixsite.com/quick-ml. Making Deep Learning through TPUs accessible to everyone. Lesser Code, faster computation, better modelling.
Home-page: https://gitlab.com/antoreep_jana/quick_ml
Download-URL: https://gitlab.com/antoreep_jana/quick_ml/-/archive/v1.3.22/quick_ml-v1.3.22.tar.gz
Author: Antoreep Jana
Author-email: antoreepjana@gmail.com
License: MIT
Keywords: quick_ml,quick ml,TPU,Distributed Training,GPU,Multi GPU Training,Deep Learning TPU,tensorflow,deep learning
Classifier: Development Status :: 5 - Production/Stable
Classifier: Intended Audience :: Developers
Classifier: Topic :: Software Development :: Build Tools
Classifier: License :: OSI Approved :: MIT License
Classifier: Programming Language :: Python :: 3
Classifier: Programming Language :: Python :: 3.4
Classifier: Programming Language :: Python :: 3.5
Classifier: Programming Language :: Python :: 3.6
Classifier: Programming Language :: Python :: 3.7
Classifier: Programming Language :: Python :: 3.8
Classifier: Programming Language :: Python :: 3.9
Classifier: Programming Language :: Python :: 3.10
Classifier: Programming Language :: Python :: 3.11
License-File: LICENSE
Requires-Dist: tensorflow<=2.19.1
Dynamic: author
Dynamic: author-email
Dynamic: classifier
Dynamic: description
Dynamic: description-content-type
Dynamic: download-url
Dynamic: home-page
Dynamic: keywords
Dynamic: license
Dynamic: license-file
Dynamic: requires-dist
Dynamic: summary
